Metadata-Version: 1.1
Name: yyyymmdd
Version: 0.1.2
Summary: Convenient Date and DateRange classes.
Home-page: https://github.com/shx2/yyyymmdd
Author: shx2
Author-email: shx222@gmail.com
License: MIT
Keywords: date datetime range
Platform: POSIX
Platform: Windows
Classifier: Programming Language :: Python :: 3
Classifier: Development Status :: 3 - Alpha
Classifier: Intended Audience :: Developers
Classifier: Topic :: Software Development
Classifier: License :: OSI Approved :: MIT License
Classifier: Operating System :: POSIX
Classifier: Operating System :: Microsoft :: Windows
